gazpar2mqtt/__init__.py
gazpar2mqtt/__main__.py
gazpar2mqtt/bridge.py
gazpar2mqtt/config_utils.py
gazpar2mqtt/gazpar.py
gazpar2mqtt/homeassistant.py
gazpar2mqtt/version.py
gazpar2mqtt-0.2.4.dist-info/METADATA
gazpar2mqtt-0.2.4.dist-info/WHEEL
gazpar2mqtt-0.2.4.dist-info/licenses/LICENSE
gazpar2mqtt-0.2.4.dist-info/RECORD
