Metadata-Version: 2.4
Name: gazpar2mqtt
Version: 0.2.4
Summary: Gateway that read GrDF meter data and publish them on MQTT queue
License: MIT License
License-File: LICENSE
Author: Stéphane Senart
Requires-Python: >=3.10
Classifier: Programming Language :: Python :: 3.10
Classifier: Programming Language :: Python :: 3.11
Classifier: Programming Language :: Python :: 3.12
Classifier: Programming Language :: Python :: 3.13
Requires-Dist: jinja2 (>=3.1.5)
Requires-Dist: paho-mqtt (>=2.1.0)
Requires-Dist: pygazpar (>=1.3.1)
Requires-Dist: pyyaml (>=6.0.2)
